MANIFEST.in
README.rst
setup.py
bin/themodulex-cl-script
test/test_tmx.py
themodulex/__init__.py
themodulex/content.py
themodulex.egg-info/PKG-INFO
themodulex.egg-info/SOURCES.txt
themodulex.egg-info/dependency_links.txt
themodulex.egg-info/not-zip-safe
themodulex.egg-info/requires.txt
themodulex.egg-info/top_level.txt