Metadata-Version: 1.1
Name: themodulex
Version: 0.2
Summary: Common utility functions for AI and Robotics research.
Home-page: http://github.com/shubhamcxz
Author: Shubham CXZ
Author-email: shubhamcxz@gmail.com
License: MIT
Keywords: Artificial Intelligence Robotics Research Python AI ML Deep Learning
Platform: UNKNOWN
Classifier: License :: OSI Approved :: MIT License
Classifier: Programming Language :: Python :: 3.5
